{
  "enhanced_scraping_session": {
    "target_match_id": 2385305,
    "num_matches_requested": 1,
    "matches_found": 1,
    "scraped_date": "2025-09-14T22:52:43.655790Z"
  },
  "matches": [
    {
      "match_id": "hltv_match_2385586",
      "hltv_match_id": 2385586,
      "date": "2025-09-14T17:30:00Z",
      "tournament": "PrizePicks NA Revival Series 9",
      "winner": "team1",
      "score": {
        "team1": 2,
        "team2": 0
      },
      "map_veto": {
        "winner_map": "Train",
        "loser_map": "Overpass",
        "decider": "Ancient"
      },
      "head_to_head": {
        "winner_head2head_freq": null,
        "loser_head2head_freq": null,
        "winner_head2head_percentage": null,
        "loser_head2head_percentage": null
      },
      "team1": {
        "name": "Marsborne",
        "team_averages": {
          "DPR": 0.67,
          "KAST": 70.88,
          "ADR": 73.92,
          "KPR": 0.69,
          "RATING": 1.07
        },
        "players": [
          {
            "name": "wolfy",
            "statistics": {
              "DPR": 0.62,
              "KAST": 71.9,
              "ADR": 70.8,
              "KPR": 0.69,
              "RATING": 1.09
            }
          },
          {
            "name": "motm",
            "statistics": {
              "DPR": 0.68,
              "KAST": 71.0,
              "ADR": 75.6,
              "KPR": 0.71,
              "RATING": 1.08
            }
          },
          {
            "name": "viz",
            "statistics": {
              "DPR": 0.67,
              "KAST": 71.6,
              "ADR": 72.6,
              "KPR": 0.66,
              "RATING": 1.04
            }
          },
          {
            "name": "chop",
            "statistics": {
              "DPR": 0.66,
              "KAST": 70.2,
              "ADR": 72.6,
              "KPR": 0.67,
              "RATING": 1.04
            }
          },
          {
            "name": "grizz",
            "statistics": {
              "DPR": 0.7,
              "KAST": 69.7,
              "ADR": 78.0,
              "KPR": 0.72,
              "RATING": 1.08
            }
          }
        ]
      },
      "team2": {
        "name": "Getting Info",
        "team_averages": {
          "DPR": 0.66,
          "KAST": 72.48,
          "ADR": 77.18,
          "KPR": 0.71,
          "RATING": 1.1
        },
        "players": [
          {
            "name": "marke",
            "statistics": {
              "DPR": 0.65,
              "KAST": 73.0,
              "ADR": 78.7,
              "KPR": 0.71,
              "RATING": 1.12
            }
          },
          {
            "name": "shane",
            "statistics": {
              "DPR": 0.67,
              "KAST": 72.2,
              "ADR": 71.6,
              "KPR": 0.67,
              "RATING": 1.04
            }
          },
          {
            "name": "snav",
            "statistics": {
              "DPR": 0.67,
              "KAST": 71.9,
              "ADR": 77.5,
              "KPR": 0.68,
              "RATING": 1.08
            }
          },
          {
            "name": "dea",
            "statistics": {
              "DPR": 0.63,
              "KAST": 73.7,
              "ADR": 81.3,
              "KPR": 0.77,
              "RATING": 1.21
            }
          },
          {
            "name": "slump",
            "statistics": {
              "DPR": 0.69,
              "KAST": 71.6,
              "ADR": 76.8,
              "KPR": 0.72,
              "RATING": 1.07
            }
          }
        ]
      },
      "metadata": {
        "match_type": "bo3",
        "event_type": "online",
        "scraped_date": "2025-09-14T22:52:43.655639Z",
        "hltv_url": "https://www.hltv.org/matches/2385586/marsborne-vs-getting-info-prizepicks-na-revival-series-9"
      }
    }
  ]
}